avis/__init__.py
avis/py.typed
avis/utils.py
avispy-0.1.0.dist-info/METADATA
avispy-0.1.0.dist-info/WHEEL
avispy-0.1.0.dist-info/licenses/LICENSE
avispy-0.1.0.dist-info/RECORD
