Metadata-Version: 2.4
Name: avispy
Version: 0.1.0
Summary: A Python package for psychology statistics and psychometrics
Author-email: qrkks <qrkks3@gmail.com>
License: MIT
License-File: LICENSE
Keywords: psychology,psychometrics,research,statistics
Classifier: Development Status :: 3 - Alpha
Classifier: Intended Audience :: Science/Research
Classifier: License :: OSI Approved :: MIT License
Classifier: Programming Language :: Python :: 3
Classifier: Programming Language :: Python :: 3.12
Classifier: Topic :: Scientific/Engineering
Requires-Python: >=3.12
